[
  {
    "tag": "VANTA ALPHA BUILD",
    "title": "Work in progress build.",
    "date": "May 29, 2026",
    "imageUrl": "https://raw.githubusercontent.com/itsBaimedd/VANTACLIENT/main/news-icon.png",
    "featured": true,
    "enabled": true
  },
  {
    "tag": "CLIENT CORE",
    "title": "Remote news loading added",
    "date": "May 29, 2026",
    "imageUrl": "https://raw.githubusercontent.com/itsBaimedd/VANTACLIENT/main/news-icon.png",
    "featured": false,
    "enabled": false
  },
  {
    "tag": "PROFILES",
    "title": "Account switching is ready",
    "date": "Soon",
    "imageUrl": "https://raw.githubusercontent.com/itsBaimedd/VANTACLIENT/main/news-icon.png",
    "featured": false,
    "enabled": false
  }
]
